elispcomp/__init__.py
elispcomp/cli.py
elispcomp/elispcomp.el
elispcomp/misc.py
elispcomp-1.1.0.dist-info/LICENSE
elispcomp-1.1.0.dist-info/METADATA
elispcomp-1.1.0.dist-info/WHEEL
elispcomp-1.1.0.dist-info/entry_points.txt
elispcomp-1.1.0.dist-info/top_level.txt
elispcomp-1.1.0.dist-info/RECORD
