Metadata-Version: 2.1
Name: elispcomp
Version: 1.1.0
Summary: Compiling Emacs Lisp code from the command-line
Home-page: https://github.com/jamescherti/elispcomp
Author: James Cherti
Classifier: Development Status :: 5 - Production/Stable
Classifier: License :: OSI Approved :: GNU General Public License (GPL)
Classifier: License :: OSI Approved :: GNU General Public License v3 (GPLv3)
Classifier: Environment :: Console
Classifier: Environment :: Plugins
Classifier: Intended Audience :: Developers
Classifier: Intended Audience :: Information Technology
Classifier: Intended Audience :: System Administrators
Classifier: Operating System :: POSIX :: Linux
Classifier: Operating System :: POSIX :: Other
Classifier: Programming Language :: Python :: 3 :: Only
Classifier: Programming Language :: Python :: 3
Classifier: Programming Language :: Python
Classifier: Topic :: Software Development :: Build Tools
Classifier: Topic :: Software Development :: Libraries :: Python Modules
Classifier: Topic :: System :: Systems Administration
Classifier: Topic :: Text Editors
Classifier: Topic :: Utilities
Requires-Python: >=3.6, <4
License-File: LICENSE
Requires-Dist: importlib-resources; python_version <= "3.8"
